[
    {
      "name": "firstName",
      "type": "text",
      "label": "First Name",
      "validations": [
        "required"
      ],
      "valid": false,
      "errorMessage": ""
    },
    {
      "name": "lastName",
      "type": "text",
      "label": "Last Name",
      "validations": [
        "required"
      ],
      "valid": false,
      "errorMessage": ""
    },
    {
      "name": "email",
      "type": "email",
      "label": "Email",
      "validations": [
        "required",
        "email"
      ],
      "valid": false,
      "errorMessage": ""
    },
    {
      "name": "password",
      "type": "password",
      "label": "Password",
      "validations": [
        "required",
        "password"
      ],
      "valid": false,
      "errorMessage": ""
    },
    {
      "name": "confirmPassword",
      "type": "password",
      "label": "Confirm Password",
      "validations": [
        "required",
        "confirmPassword"
      ],
      "valid": false,
      "errorMessage": ""
    }
  ]